alphanet/__init__.py
alphanet/data.py
alphanet/metrics.py
alphanet-0.0.20.dist-info/LICENSE.txt
alphanet-0.0.20.dist-info/METADATA
alphanet-0.0.20.dist-info/WHEEL
alphanet-0.0.20.dist-info/top_level.txt
alphanet-0.0.20.dist-info/RECORD
