Metadata-Version: 2.1
Name: alphanet
Version: 0.0.20
Summary: A recurrent neural network for predicting stock market performance
Home-page: https://github.com/Congyuwang/AlphaNetV3
Author: Congyu Wang
Author-email: leonwang998@foxmail.com
License: MIT License
Platform: UNKNOWN
Classifier: Programming Language :: Python :: 3
Classifier: License :: OSI Approved :: MIT License
Classifier: Operating System :: OS Independent
Requires-Python: >=3.6
License-File: LICENSE.txt
